setup.cfg
setup.py
vzzual/OLD_api.py
vzzual/__init__.py
vzzual/api.py
vzzual/version.py
vzzual.egg-info/PKG-INFO
vzzual.egg-info/SOURCES.txt
vzzual.egg-info/dependency_links.txt
vzzual.egg-info/requires.txt
vzzual.egg-info/top_level.txt