Metadata-Version: 1.1
Name: vzzual
Version: 0.0.3
Summary: Official python wrapper for the Vzzual API
Home-page: https://github.com/vzzual/vzzual-python
Author: Vzzual
Author-email: support@vzzual.com
License: MIT License
Platform: UNKNOWN
Classifier: Development Status :: 4 - Beta
Classifier: Intended Audience :: Developers
Classifier: License :: OSI Approved :: MIT License
Classifier: Programming Language :: Python :: 2.7
Classifier: Programming Language :: Python :: 3.3
Classifier: Programming Language :: Python :: 3.4
